rfq/__init__.py
rfq/consume.py
rfq/harvest.py
rfq/info.py
rfq/listq.py
rfq/peek.py
rfq/publish.py
rfq/purge.py
rfq/py.typed
rfq/redis.py
rfq/rfq.py
rfq/scripts/__init__.py
rfq/scripts/__main__.py
rfq/scripts/completions.py
rfq/scripts/consume.py
rfq/scripts/harvest.py
rfq/scripts/info.py
rfq/scripts/listq.py
rfq/scripts/peek.py
rfq/scripts/publish.py
rfq/scripts/purge.py
rfq/scripts/topics.py
rfq/scripts/version.py
rfq/topics.py
rfq/version.py
rfq-1.4.0.dist-info/entry_points.txt
rfq-1.4.0.dist-info/LICENSE.md
rfq-1.4.0.dist-info/WHEEL
rfq-1.4.0.dist-info/METADATA
rfq-1.4.0.dist-info/RECORD
