Metadata-Version: 2.1
Name: rfq
Version: 1.4.0
Summary: Simple language-agnostic message queues: tools, conventions, examples
License: MIT
Author: Robofarm
Author-email: hello@robofarm.io
Requires-Python: >=3.8,<4.0
Classifier: License :: OSI Approved :: MIT License
Classifier: Programming Language :: Python :: 3
Classifier: Programming Language :: Python :: 3.8
Provides-Extra: hiredis
Requires-Dist: hiredis (>=1.1.0,<2.0.0); extra == "hiredis"
Requires-Dist: redis (>=3.5.3,<4.0.0)
